MANIFEST.in
setup.cfg
setup.py
inclose_package/In-Close4.cpp
inclose_package/In-Close4.h
inclose_package/crossplatform.cpp
inclose_package/crossplatform.h
inclose_package/gen_inclose.py
inclose_package/hr_time.cpp
inclose_package/hr_time.h
inclose_package/stdafx.cpp
inclose_package/stdafx.h
inclose_package/targetver.h
pynclose/__init__.py
pynclose/__main__.py
pynclose/cli.py
pynclose/export.py
pynclose/extract.py
pynclose.egg-info/PKG-INFO
pynclose.egg-info/SOURCES.txt
pynclose.egg-info/dependency_links.txt
pynclose.egg-info/not-zip-safe
pynclose.egg-info/requires.txt
pynclose.egg-info/top_level.txt