Metadata-Version: 1.1
Name: pynclose
Version: 0.0.6
Summary: wrapper around an in-close implementation
Home-page: https://github.com/aluriak/pynclose
Author: Lucas Bourneuf
Author-email: lucas.bourneuf@laposte.net
License: GPL
Keywords: Formal Concept Analysis,Answer Set Programming
Platform: UNKNOWN
Classifier: Development Status :: 4 - Beta
Classifier: Intended Audience :: Developers
Classifier: Programming Language :: Python :: 3
Classifier: Programming Language :: Python :: 3.5
